client/Client.py
client/__init__.py
pyfaceplateclient/__init__.py
pyfaceplateclient/ecomet.py
pyfaceplateclient/test.py
PyFaceplateClient-0.0.2.dist-info/LICENSE
PyFaceplateClient-0.0.2.dist-info/METADATA
PyFaceplateClient-0.0.2.dist-info/WHEEL
PyFaceplateClient-0.0.2.dist-info/top_level.txt
PyFaceplateClient-0.0.2.dist-info/RECORD
