Metadata-Version: 2.1
Name: PyFaceplateClient
Version: 0.0.2
Summary: Client for Faceplate powered by Ecomet database
Home-page: https://github.com/rkrikbaev/pyfaceplateclient
Author: Rustam Krikbayev
Author-email: rkrikbaev@gmail.com
License: UNKNOWN
Platform: UNKNOWN
Classifier: Programming Language :: Python :: 3
Classifier: License :: OSI Approved :: MIT License
Classifier: Operating System :: OS Independent
Requires-Python: >=3.6
